[
    {
        "id": 1,
        "name": "Absolut Zero",
        "price": 19.99,
        "image": "./img/aboslutezero.png"
    },
    
    {
        "id": 2,
        "name": "Lemon Burst",
        "price": 19.99,
        "image": "./img/lemonburst.png"
    },

    {
        "id": 3,
        "name": "Bluebery Twister",
        "price": 19.99,
        "image": "./img/blueberrytwister.png"
    },
    
    {
        "id": 4,
        "name": "Strawberry Punch",
        "price": 19.99,
        "image": "./img/strawberrypunch.png"}
]
